livesync/__init__.py
livesync/py.typed
livesync/types.py
livesync/_protos/remote_layer/__init__.py
livesync/_protos/remote_layer/remote_layer_pb2.py
livesync/_protos/remote_layer/remote_layer_pb2.pyi
livesync/_protos/remote_layer/remote_layer_pb2_grpc.py
livesync/_utils/__init__.py
livesync/_utils/graph_visualizer.py
livesync/_utils/logs.py
livesync/_utils/naming.py
livesync/_utils/round_robin_selector.py
livesync/_utils/string_transformers.py
livesync/callbacks/__init__.py
livesync/callbacks/callbacks.py
livesync/callbacks/events.py
livesync/callbacks/protocol.py
livesync/frames/__init__.py
livesync/frames/audio_frame.py
livesync/frames/base_frame.py
livesync/frames/video_frame.py
livesync/layers/__init__.py
livesync/layers/layer.py
livesync/layers/audio/__init__.py
livesync/layers/audio/audio_recorder.py
livesync/layers/audio/microphone.py
livesync/layers/core/__init__.py
livesync/layers/core/callable_layer.py
livesync/layers/core/input_layer.py
livesync/layers/core/lambda_layer.py
livesync/layers/core/merge_layer.py
livesync/layers/core/split_layer.py
livesync/layers/media/__init__.py
livesync/layers/media/media_recorder.py
livesync/layers/media/media_synchronizer.py
livesync/layers/numeric/__init__.py
livesync/layers/numeric/multiply.py
livesync/layers/numeric/periodic_constant.py
livesync/layers/operators/__init__.py
livesync/layers/operators/delay.py
livesync/layers/remote/__init__.py
livesync/layers/remote/remote.py
livesync/layers/remote/server/__init__.py
livesync/layers/remote/server/remote_layer_server.py
livesync/layers/remote/server/remote_layer_servicer.py
livesync/layers/video/__init__.py
livesync/layers/video/fps_control.py
livesync/layers/video/video_quality_control.py
livesync/layers/video/video_recorder.py
livesync/layers/video/watermark.py
livesync/layers/video/webcam.py
livesync/streams/__init__.py
livesync/streams/stream.py
livesync/sync/__init__.py
livesync/sync/run_handle.py
livesync/sync/runner.py
livesync/sync/sync.py
livesync_io-0.3.16.dist-info/METADATA
livesync_io-0.3.16.dist-info/WHEEL
livesync_io-0.3.16.dist-info/entry_points.txt
livesync_io-0.3.16.dist-info/licenses/LICENSE
livesync_io-0.3.16.dist-info/RECORD
