Metadata-Version: 2.3
Name: livesync-io
Version: 0.3.16
Summary: The graph-based video processing framework
Project-URL: Homepage, https://github.com/os-designers/livesync
Project-URL: Repository, https://github.com/os-designers/livesync
Author-email: LiveSync <support@live-sync.io>
License: MIT
Classifier: Intended Audience :: Developers
Classifier: License :: OSI Approved :: MIT License
Classifier: Operating System :: MacOS
Classifier: Operating System :: Microsoft :: Windows
Classifier: Operating System :: OS Independent
Classifier: Operating System :: POSIX
Classifier: Operating System :: POSIX :: Linux
Classifier: Programming Language :: Python :: 3.10
Classifier: Programming Language :: Python :: 3.11
Classifier: Programming Language :: Python :: 3.12
Classifier: Topic :: Software Development :: Libraries :: Python Modules
Classifier: Typing :: Typed
Requires-Python: >=3.10
Requires-Dist: av>=14.0.1
Requires-Dist: ffmpeg-python>=0.2.0
Requires-Dist: grpcio<2.0.0,>=1.68.1
Requires-Dist: httpx>=0.25.2
Requires-Dist: numpy<3.0.0,>=1.21.6
Requires-Dist: opencv-python>=4.10.0.84
Requires-Dist: protobuf>=4.23.2
Requires-Dist: pyaudio>=0.2.14
Requires-Dist: typing-extensions>=4.12.2
